guardian/__init__.py
guardian/base.py
guardian/config.py
guardian/core.py
guardian/dsl.py
guardian/flow.py
guardian/jwt.py
guardian/types.py
kingdom_guardian-0.0.1.dev2.dist-info/LICENSE
kingdom_guardian-0.0.1.dev2.dist-info/WHEEL
kingdom_guardian-0.0.1.dev2.dist-info/METADATA
kingdom_guardian-0.0.1.dev2.dist-info/RECORD
